pstm/__init__.py
pstm/__version__.py
pstm/base.py
pstm/demand.py
pstm/ev.py
pstm/gas_boiler.py
pstm/heat_pump.py
pstm/household_vdi4655.py
pstm/mastr.py
pstm/mastr_converter.py
pstm/p2h.py
pstm/pv.py
pstm/py.typed
pstm/storage.py
pstm/wind.py
pstm/dickert/__init__.py
pstm/dickert/appliances.py
pstm/dickert/baseline_profiles.py
pstm/dickert/cycle_profiles.py
pstm/dickert/households.py
pstm/dickert/lighting_profiles.py
pstm/dickert/on_off_profiles.py
pstm/dickert/process_profiles.py
pstm/utils/__init__.py
pstm/utils/dates.py
pstm/utils/exceptions.py
pstm/utils/geo.py
pstm/utils/roughness_lengths.py
pstm/utils/weather.py
pyramecium_technology_models-1.1.0.dist-info/METADATA
pyramecium_technology_models-1.1.0.dist-info/WHEEL
pyramecium_technology_models-1.1.0.dist-info/entry_points.txt
pyramecium_technology_models-1.1.0.dist-info/licenses/LICENSE
pyramecium_technology_models-1.1.0.dist-info/RECORD
