Metadata-Version: 2.4
Name: pyramecium-technology-models
Version: 1.1.0
Summary: A toolbox to create multi-energy power time series for different technologies in steady-state simulations of energy systems.
Project-URL: homepage, https://github.com/ieeh-tu-dresden/power-system-technology-models
Author: Guntram Pressmair, Jörg Dickert
Author-email: Sasan Jacob Rasti <sasan_jacob.rasti@tu-dresden.de>, Felix Flatter <felix.flatter@rptu.de>
License: BSD 3-Clause License
License-File: LICENSE
Requires-Python: >=3.12
Requires-Dist: aiofiles>=24.1.0
Requires-Dist: aiohttp[speedups]>=3.10.2
Requires-Dist: attrs>=24.2.0
Requires-Dist: cattrs>=23.2.3
Requires-Dist: click>=8.1.7
Requires-Dist: geopandas>=1.0.1
Requires-Dist: loguru>=0.7.2
Requires-Dist: matplotlib>=3.9.1.post1
Requires-Dist: netcdf4>=1.7.1.post1
Requires-Dist: numpy>=2.0.1
Requires-Dist: open-mastr>=0.14.4
Requires-Dist: openpyxl>=3.1.5
Requires-Dist: pandas>=2.2.2
Requires-Dist: pvlib>=0.11.0
Requires-Dist: pyarrow>=17.0.0
Requires-Dist: pyproj>=3.6.1
Requires-Dist: pyyaml>=6.0.2
Requires-Dist: rasterio>=1.3.10
Requires-Dist: requests>=2.32.3
Requires-Dist: scipy>=1.14.0
Requires-Dist: shapely>=2.0.5
Requires-Dist: tqdm>=4.66.5
Requires-Dist: windpowerlib>=0.2.2
